regularization_derivative/__init__.py
regularization_derivative/regularization_derivative.py
regularization_derivative-0.0.4.dist-info/LICENSE.md
regularization_derivative-0.0.4.dist-info/METADATA
regularization_derivative-0.0.4.dist-info/WHEEL
regularization_derivative-0.0.4.dist-info/top_level.txt
regularization_derivative-0.0.4.dist-info/RECORD
