Metadata-Version: 2.1
Name: regularization-derivative
Version: 0.0.4
Summary: A package for computing derived data with errors
Home-page: https://github.com/arina-radivon/regularization_method
Author: Arina Radivon
Author-email: radivon.av@phystech.edu
License: UNKNOWN
Platform: UNKNOWN
Classifier: Programming Language :: Python :: 3
Classifier: License :: OSI Approved :: MIT License
Classifier: Operating System :: OS Independent
License-File: LICENSE.md
Requires-Dist: numpy (==1.23.2)
Requires-Dist: scipy (==1.9.1)
Requires-Dist: tqdm (==4.65.0)
Requires-Dist: setuptools (==57.4.0)
